hibpcli/__init__.py
hibpcli/cli.py
hibpcli/exceptions.py
hibpcli/keepass.py
hibpcli/leaks.py
hibpcli-0.6.0.dist-info/LICENSE
hibpcli-0.6.0.dist-info/METADATA
hibpcli-0.6.0.dist-info/WHEEL
hibpcli-0.6.0.dist-info/entry_points.txt
hibpcli-0.6.0.dist-info/top_level.txt
hibpcli-0.6.0.dist-info/zip-safe
hibpcli-0.6.0.dist-info/RECORD
