Metadata-Version: 2.1
Name: hibpcli
Version: 0.6.0
Summary: A command line interface for the **haveibeenpwned.com** API - speaks keepass.
Home-page: https://github.com/jugmac00/hibpcli
Author: Jürgen Gmach
Author-email: juergen.gmach@goglemail.com
License: MIT
Platform: UNKNOWN
Classifier: License :: OSI Approved :: MIT License
Classifier: Programming Language :: Python
Classifier: Programming Language :: Python :: 3.6
Classifier: Programming Language :: Python :: 3.7
Classifier: Programming Language :: Python :: 3.8
Classifier: Programming Language :: Python :: 3.9
Classifier: Programming Language :: Python :: 3.10
Classifier: Development Status :: 4 - Beta
Classifier: Environment :: Console
License-File: LICENSE
Requires-Dist: click (>=7.1.2)
Requires-Dist: pykeepass (>=4.0.1)
Requires-Dist: httpx (>=0.13.3)
Provides-Extra: dev
Requires-Dist: pdbpp ; extra == 'dev'
Provides-Extra: test
Requires-Dist: pytest ; extra == 'test'
Requires-Dist: coverage ; extra == 'test'
